graphqlnomad/__init__.py
graphqlnomad/__main__.py
graphqlnomad/nomad.py
graphqlnomad-1.0.1.dist-info/licenses/LICENSE
graphqlnomad-1.0.1.dist-info/METADATA
graphqlnomad-1.0.1.dist-info/WHEEL
graphqlnomad-1.0.1.dist-info/entry_points.txt
graphqlnomad-1.0.1.dist-info/top_level.txt
graphqlnomad-1.0.1.dist-info/RECORD
