Metadata-Version: 2.4
Name: graphqlnomad
Version: 1.0.1
Summary: An integrated tool to detect, fingerprint, and explore GraphQL endpoints.
Home-page: https://github.com/CYBWithFlourish/GraphQLNomad
Author: CYBWithFlourish
Author-email: project. samclak@gmail.com
License: Apache-2.0
Classifier: Programming Language :: Python :: 3
Classifier: License :: OSI Approved :: Apache Software License
Classifier: Operating System :: OS Independent
Classifier: Environment :: Console
Classifier: Topic :: Security
Requires-Python: >=3.6
License-File: LICENSE
Requires-Dist: requests
Requires-Dist: colorama
Dynamic: author
Dynamic: author-email
Dynamic: classifier
Dynamic: description
Dynamic: description-content-type
Dynamic: home-page
Dynamic: license
Dynamic: license-file
Dynamic: requires-dist
Dynamic: requires-python
Dynamic: summary
